gs_gitflow/main.py
gs_gitflow-0.1.0.dist-info/LICENSE
gs_gitflow-0.1.0.dist-info/METADATA
gs_gitflow-0.1.0.dist-info/WHEEL
gs_gitflow-0.1.0.dist-info/RECORD
