Metadata-Version: 2.1
Name: gs_gitflow
Version: 0.1.0
Summary: Uma implementação gitflow
License: MIT
Author: Guionardo
Author-email: guionardo@gmail.com
Requires-Python: >=3.8,<4.0
Classifier: License :: OSI Approved :: MIT License
Classifier: Programming Language :: Python :: 3
Classifier: Programming Language :: Python :: 3.8
Classifier: Programming Language :: Python :: 3.9
Classifier: Programming Language :: Python :: 3.10
Classifier: Programming Language :: Python :: 3.11
Requires-Dist: packaging (>=23.2,<24.0)
